{"assets_configuration.md":"DEWythHJ","assets_index.md":"C6TZqiQz","basic_configuration.md":"edAQLRei","basic_index.md":"u66o9TEX","body_configuration.md":"jQl17hv8","body_helpers.md":"KXGImEdj","body_index.md":"C9GpVuYk","cookie_helpers.md":"Bh7tuuik","cookie_index.md":"C_pG_Du5","cors_helpers.md":"_PguqYHP","cors_index.md":"DoFbBmyZ","decorators_controllers.md":"CHXtUva6","decorators_index.md":"DEq234Yq","decorators_parameters.md":"WsNtAV16","i18n_index.md":"hCMsvVup","index.md":"BiPjgAFl","logger_helpers.md":"DnkEFgtb","logger_index.md":"BQ1WKcbE","prometheus_configuration.md":"BwKOSj0e","prometheus_index.md":"BfFv0obP","query_helpers.md":"Dc8WgD7b","query_index.md":"B8OicBMM","rate-limit-redis_index.md":"CM1Kj8nk","rate-limit_configuration.md":"CHf8Tvan","rate-limit_index.md":"Cra3WnwG","swagger-ui_index.md":"DyNpFbKR"}
